LICENSE
MANIFEST.in
README.rst
setup.py
django_arakoon_cache/__init__.py
django_arakoon_cache/cache.py
django_arakoon_cache.egg-info/PKG-INFO
django_arakoon_cache.egg-info/SOURCES.txt
django_arakoon_cache.egg-info/dependency_links.txt
django_arakoon_cache.egg-info/requires.txt
django_arakoon_cache.egg-info/top_level.txt