Metadata-Version: 1.1
Name: django-arakoon-cache
Version: 0.1.0
Summary: Arakoon cache backend for Django.
Home-page: https://github.com/mohabusama/django-arakoon-cache
Author: Mohab Usama
Author-email: mohab.usama@gmail.com
License: The MIT License (MIT)
